enrichsdk/__init__.py
enrichsdk/__pycache__/__init__.cpython-37.pyc
enrichsdk/api/__init__.py
enrichsdk/api/draw.py
enrichsdk/api/__pycache__/__init__.cpython-37.pyc
enrichsdk/api/__pycache__/draw.cpython-37.pyc
enrichsdk/app/flask/render.py
enrichsdk/app/flask/__pycache__/render.cpython-37.pyc
enrichsdk/app/flask/static/bootstrap/fonts/glyphicons-halflings-regular.eot
enrichsdk/app/flask/static/bootstrap/fonts/glyphicons-halflings-regular.svg
enrichsdk/app/flask/static/bootstrap/fonts/glyphicons-halflings-regular.ttf
enrichsdk/app/flask/static/bootstrap/js/bootstrap.js
enrichsdk/app/flask/static/bootstrap/js/bootstrap.min.js
enrichsdk/app/flask/static/bootstrap/themes/amelia/css/bootstrap.css
enrichsdk/app/flask/static/bootstrap/themes/amelia/css/bootstrap.min.css
enrichsdk/app/flask/static/bootstrap/themes/cerulean/css/bootstrap.css
enrichsdk/app/flask/static/bootstrap/themes/cerulean/css/bootstrap.min.css
enrichsdk/app/flask/static/bootstrap/themes/cosmo/css/bootstrap.css
enrichsdk/app/flask/static/bootstrap/themes/cosmo/css/bootstrap.min.css
enrichsdk/app/flask/static/bootstrap/themes/cyborg/css/bootstrap.css
enrichsdk/app/flask/static/bootstrap/themes/cyborg/css/bootstrap.min.css
enrichsdk/app/flask/static/bootstrap/themes/darkly/css/bootstrap.css
enrichsdk/app/flask/static/bootstrap/themes/darkly/css/bootstrap.min.css
enrichsdk/app/flask/static/bootstrap/themes/default/css/bootstrap.css
enrichsdk/app/flask/static/bootstrap/themes/default/css/bootstrap.min.css
enrichsdk/app/flask/static/bootstrap/themes/flatly/css/bootstrap.css
enrichsdk/app/flask/static/bootstrap/themes/flatly/css/bootstrap.min.css
enrichsdk/app/flask/static/bootstrap/themes/journal/css/bootstrap.css
enrichsdk/app/flask/static/bootstrap/themes/journal/css/bootstrap.min.css
enrichsdk/app/flask/static/bootstrap/themes/lumen/css/bootstrap.css
enrichsdk/app/flask/static/bootstrap/themes/lumen/css/bootstrap.min.css
enrichsdk/app/flask/static/bootstrap/themes/readable/css/bootstrap.css
enrichsdk-3.0.2.dist-info/LICENSE
enrichsdk-3.0.2.dist-info/METADATA
enrichsdk-3.0.2.dist-info/WHEEL
enrichsdk-3.0.2.dist-info/entry_points.txt
enrichsdk-3.0.2.dist-info/top_level.txt
enrichsdk-3.0.2.dist-info/RECORD
