Metadata-Version: 2.1
Name: enrichsdk
Version: 3.0.2
Summary: Enrich Developer Kit
Home-page: http://github.com/pingali/scribble-enrichsdk
Author: Venkata Pingali
Author-email: pingali@scribbledata.io
License: All rights reserved
Platform: UNKNOWN
Classifier: Programming Language :: Python :: 3
Classifier: Operating System :: OS Independent
Requires-Python: >=3.6
Requires-Dist: docutils (<0.16)
Requires-Dist: click (>=6.7)
Requires-Dist: botocore (==1.17.44)
Requires-Dist: boto3 (==1.14.14)
Requires-Dist: sphinx-click (==2.3.0)
Requires-Dist: glob2 (==0.5)
Requires-Dist: requests (>=2.21.0)
Requires-Dist: requests-oauthlib (==0.8.0)
Requires-Dist: pytest (>=4.6.0)
Requires-Dist: numpy (>=1.14.2)
Requires-Dist: numpydoc (>=0.7.0)
Requires-Dist: pandas (>=0.22.0)
Requires-Dist: idna (==2.8)
Requires-Dist: coverage (==4.4.1)
Requires-Dist: flake8 (==3.4.1)
Requires-Dist: raven (==6.6.0)
Requires-Dist: python-json-logger (==0.1.8)
Requires-Dist: python-dateutil (==2.8.1)
Requires-Dist: s3fs (>=0.3.5)
Requires-Dist: colored (==1.3.5)
Requires-Dist: flask-multistatic (==1.0)
Requires-Dist: humanize (==0.5.1)
Requires-Dist: pytz (==2020.1)
Requires-Dist: Flask (==1.1.2)
Requires-Dist: Jinja2 (>=2.10.1)
Requires-Dist: pytest-cov
Requires-Dist: Markdown (>=3.0.20)
Requires-Dist: prompt-toolkit (>=2.0.10)
Requires-Dist: pyarrow (>=0.9.0)
Requires-Dist: cytoolz (==0.9.0.1)
Requires-Dist: moto (>=1.3.14)
Requires-Dist: prefect (>=0.7.0)
Requires-Dist: distro (>=1.4.0)
Requires-Dist: gcsfs
Requires-Dist: jupyter-core (>=4.6.1)
Requires-Dist: nbformat (>=4.4.0)
Requires-Dist: tzlocal (>=2.0.0)
Requires-Dist: texttable
Requires-Dist: pykafka
Requires-Dist: redis
Requires-Dist: gitpython
Requires-Dist: logstash-formatter
Requires-Dist: pyhive
Requires-Dist: pyfiglet
Requires-Dist: sqlalchemy
